AlgoMaster/__init__.py
AlgoMaster/classifier.py
AlgoMaster/regressor.py
AlgoMaster-0.1.3.dist-info/METADATA
AlgoMaster-0.1.3.dist-info/WHEEL
AlgoMaster-0.1.3.dist-info/top_level.txt
AlgoMaster-0.1.3.dist-info/RECORD
