Metadata-Version: 2.1
Name: AlgoMaster
Version: 0.1.3
Summary: The Regression class simplifies regression analysis by providing a convenient and flexible approach for model training, evaluation, and hyperparameter tuning.The Classifier class streamlines classification tasks by offering a well-organized framework for model selection, hyperparameter tuning, 
Author: sajo sam
Author-email: <sajosamambalakara@gmail.com>
Keywords: machine learning,classifiers,logistic regression,k-nearest neighbors,naive Bayes,random forests,support vector machines,ensemble methods,hyperparameter tuning,performance evaluation,comparison,multiple classifiersadvantages,Regression class,regression analysis, Python,model training,evaluation,hyperparameter tuning,encapsulating,regression algorithms,metrics,simplifies,building,comparing,regression models,accurate predictions,insights
Classifier: Development Status :: 1 - Planning
Classifier: Intended Audience :: Developers
Classifier: Programming Language :: Python :: 3
Classifier: Operating System :: Unix
Classifier: Operating System :: MacOS :: MacOS X
Classifier: Operating System :: Microsoft :: Windows
Requires-Dist: pandas
Requires-Dist: numpy
Requires-Dist: xgboost
Requires-Dist: scikit-learn
